simple_noaa/__init__.py
simple_noaa/main.py
simple_NOAA-0.1.dist-info/METADATA
simple_NOAA-0.1.dist-info/WHEEL
simple_NOAA-0.1.dist-info/top_level.txt
simple_NOAA-0.1.dist-info/RECORD
