Metadata-Version: 2.1
Name: simple-NOAA
Version: 0.1
Summary: simple_NOAA allows for streamlined access to NOAA datasets
Home-page: https://github.com/yourusername/mypackage
Author: Devin Shaw
Author-email: your.email@example.com
Keywords: NOAA Climate Data
Classifier: Development Status :: 3 - Alpha
Classifier: Intended Audience :: Developers
Classifier: License :: OSI Approved :: MIT License
Classifier: Programming Language :: Python :: 3.6
Classifier: Programming Language :: Python :: 3.7
Classifier: Programming Language :: Python :: 3.8
Requires-Dist: pandas
Requires-Dist: requests
Requires-Dist: io
Requires-Dist: shapely
